{
  "devices": {
    "total": 516,
    "active": 132,
    "nonCompliant": 100,
    "discovered": 123,
    "byType": {
      "smartphone": 110,
      "tablet": 107,
      "laptop": 84,
      "IoT": 105,
      "gateway": 110
    },
    "byOS": {
      "iOS": 140,
      "Android": 124,
      "Windows": 123,
      "Other": 129
    },
    "byCarrier": {
      "AT&T": 90,
      "Verizon": 108,
      "T-Mobile": 108,
      "Sprint": 113,
      "US Cellular": 97
    }
  },
  "policies": {
    "total": 39,
    "active": 20,
    "byPriority": {
      "low": 11,
      "medium": 8,
      "high": 13,
      "critical": 7
    },
    "enforcementStats": {
      "total": 20473,
      "violations": 2128,
      "autoRemediated": 1010
    }
  },
  "towers": {
    "total": 10,
    "active": 2,
    "byCarrier": {
      "AT&T": 4,
      "Verizon": 5,
      "T-Mobile": 7,
      "Sprint": 2,
      "US Cellular": 4
    },
    "byStatus": {
      "active": 2,
      "maintenance": 2,
      "inactive": 6
    }
  },
  "security": {
    "complianceScore": 95,
    "criticalAlerts": 4,
    "recentIncidents": [
      {
        "id": "35b7b51b-055c-43d7-80ba-44116df982fc",
        "type": "policy_violation",
        "severity": "high",
        "description": "Suscipio degero cultura cornu.",
        "timestamp": "2025-05-28T07:31:44.708Z",
        "affectedEntities": [
          {
            "type": "policy",
            "id": "50dec93a-7073-44ba-b940-9767a71411ec"
          },
          {
            "type": "device",
            "id": "8aa9f861-b014-476f-88e7-381f18ba7785"
          }
        ],
        "status": "investigating",
        "resolution": {
          "action": "Alienus voveo demoror velut amaritudo.",
          "resolvedBy": "c07d2fc5-25b1-4d39-aa1c-2531779226f7",
          "resolvedAt": "2025-06-03T08:17:50.108Z"
        }
      }
    ]
  },
  "apps": {
    "total": 34,
    "byCategory": {
      "productivity": 8,
      "security": 8,
      "communication": 5,
      "enterprise": 4,
      "custom": 9
    },
    "usageStats": {
      "totalActions": 8155,
      "violations": 5429,
      "byApp": {
        "app_00000001": {
          "total": 213,
          "violations": 141,
          "lastUsed": ""
        },
        "app_00000002": {
          "total": 252,
          "violations": 168,
          "lastUsed": ""
        },
        "app_00000003": {
          "total": 354,
          "violations": 247,
          "lastUsed": ""
        },
        "app_00000004": {
          "total": 283,
          "violations": 168,
          "lastUsed": ""
        },
        "app_00000005": {
          "total": 207,
          "violations": 139,
          "lastUsed": ""
        },
        "app_00000006": {
          "total": 303,
          "violations": 207,
          "lastUsed": ""
        },
        "app_00000007": {
          "total": 221,
          "violations": 137,
          "lastUsed": ""
        },
        "app_00000008": {
          "total": 225,
          "violations": 142,
          "lastUsed": ""
        },
        "app_00000009": {
          "total": 222,
          "violations": 148,
          "lastUsed": ""
        },
        "app_00000010": {
          "total": 237,
          "violations": 140,
          "lastUsed": ""
        },
        "app_00000011": {
          "total": 258,
          "violations": 162,
          "lastUsed": ""
        },
        "app_00000012": {
          "total": 232,
          "violations": 149,
          "lastUsed": ""
        },
        "app_00000013": {
          "total": 245,
          "violations": 164,
          "lastUsed": ""
        },
        "app_00000014": {
          "total": 241,
          "violations": 162,
          "lastUsed": ""
        },
        "app_00000015": {
          "total": 189,
          "violations": 121,
          "lastUsed": ""
        },
        "app_00000016": {
          "total": 278,
          "violations": 185,
          "lastUsed": ""
        },
        "app_00000017": {
          "total": 205,
          "violations": 152,
          "lastUsed": ""
        },
        "app_00000018": {
          "total": 256,
          "violations": 182,
          "lastUsed": ""
        },
        "app_00000019": {
          "total": 173,
          "violations": 112,
          "lastUsed": ""
        },
        "app_00000020": {
          "total": 266,
          "violations": 189,
          "lastUsed": ""
        },
        "app_00000021": {
          "total": 271,
          "violations": 184,
          "lastUsed": ""
        },
        "app_00000022": {
          "total": 263,
          "violations": 189,
          "lastUsed": ""
        },
        "app_00000023": {
          "total": 233,
          "violations": 151,
          "lastUsed": ""
        },
        "app_00000024": {
          "total": 231,
          "violations": 162,
          "lastUsed": ""
        },
        "app_00000025": {
          "total": 216,
          "violations": 152,
          "lastUsed": ""
        },
        "app_00000026": {
          "total": 290,
          "violations": 187,
          "lastUsed": ""
        },
        "app_00000027": {
          "total": 197,
          "violations": 134,
          "lastUsed": ""
        },
        "app_00000028": {
          "total": 248,
          "violations": 154,
          "lastUsed": ""
        },
        "app_00000029": {
          "total": 269,
          "violations": 182,
          "lastUsed": ""
        },
        "app_00000030": {
          "total": 235,
          "violations": 165,
          "lastUsed": ""
        },
        "app_00000031": {
          "total": 196,
          "violations": 136,
          "lastUsed": ""
        },
        "app_00000032": {
          "total": 241,
          "violations": 159,
          "lastUsed": ""
        },
        "app_00000033": {
          "total": 190,
          "violations": 120,
          "lastUsed": ""
        },
        "app_00000034": {
          "total": 215,
          "violations": 139,
          "lastUsed": ""
        }
      }
    }
  }
}