[
  {
    "id": "ent_00000001",
    "name": "Schoen and Sons Ltd",
    "tier": "premium",
    "subscription": {
      "startDate": "2024-07-17T17:44:11.901Z",
      "endDate": "2027-02-15T23:13:39.556Z",
      "status": "active",
      "tier": "standard",
      "features": {
        "autoRemediation": false,
        "realTimeMonitoring": true,
        "customPolicies": true,
        "deviceDiscovery": true,
        "apiAccess": true,
        "towerEnforcement": false,
        "appMonitoring": true
      }
    }
  },
  {
    "id": "ent_00000002",
    "name": "Wisozk LLC Ltd",
    "tier": "standard",
    "subscription": {
      "startDate": "2025-02-27T08:20:16.550Z",
      "endDate": "2026-11-28T12:41:07.345Z",
      "status": "active",
      "tier": "standard",
      "features": {
        "autoRemediation": false,
        "realTimeMonitoring": true,
        "customPolicies": true,
        "deviceDiscovery": true,
        "apiAccess": true,
        "towerEnforcement": false,
        "appMonitoring": true
      }
    }
  },
  {
    "id": "ent_00000003",
    "name": "Hirthe Inc Ltd",
    "tier": "premium",
    "subscription": {
      "startDate": "2024-10-05T23:33:00.069Z",
      "endDate": "2027-04-21T17:36:10.913Z",
      "status": "active",
      "tier": "standard",
      "features": {
        "autoRemediation": false,
        "realTimeMonitoring": true,
        "customPolicies": true,
        "deviceDiscovery": true,
        "apiAccess": true,
        "towerEnforcement": false,
        "appMonitoring": true
      }
    }
  },
  {
    "id": "ent_00000004",
    "name": "Heathcote, Jacobs and Hirthe Ltd",
    "tier": "standard",
    "subscription": {
      "startDate": "2025-01-22T04:16:54.678Z",
      "endDate": "2027-05-01T01:01:32.868Z",
      "status": "active",
      "tier": "basic",
      "features": {
        "autoRemediation": false,
        "realTimeMonitoring": true,
        "customPolicies": false,
        "deviceDiscovery": true,
        "apiAccess": false,
        "towerEnforcement": false,
        "appMonitoring": true
      }
    }
  },
  {
    "id": "ent_00000005",
    "name": "Mosciski Group Ltd",
    "tier": "premium",
    "subscription": {
      "startDate": "2025-03-14T12:32:26.391Z",
      "endDate": "2026-10-31T13:23:14.133Z",
      "status": "active",
      "tier": "enterprise",
      "features": {
        "autoRemediation": true,
        "realTimeMonitoring": true,
        "customPolicies": true,
        "deviceDiscovery": true,
        "apiAccess": true,
        "towerEnforcement": true,
        "appMonitoring": true
      }
    }
  },
  {
    "id": "ent_00000006",
    "name": "Rosenbaum - Schroeder Ltd",
    "tier": "standard",
    "subscription": {
      "startDate": "2024-10-31T03:30:19.731Z",
      "endDate": "2027-02-23T15:13:02.843Z",
      "status": "active",
      "tier": "premium",
      "features": {
        "autoRemediation": true,
        "realTimeMonitoring": true,
        "customPolicies": true,
        "deviceDiscovery": true,
        "apiAccess": true,
        "towerEnforcement": true,
        "appMonitoring": true
      }
    }
  },
  {
    "id": "ent_00000007",
    "name": "O'Connell, Morar and Schmeler Ltd",
    "tier": "standard",
    "subscription": {
      "startDate": "2025-01-08T22:35:59.521Z",
      "endDate": "2027-04-04T03:34:07.483Z",
      "status": "active",
      "tier": "premium",
      "features": {
        "autoRemediation": true,
        "realTimeMonitoring": true,
        "customPolicies": true,
        "deviceDiscovery": true,
        "apiAccess": true,
        "towerEnforcement": true,
        "appMonitoring": true
      }
    }
  },
  {
    "id": "ent_00000008",
    "name": "Kuhic Group Ltd",
    "tier": "premium",
    "subscription": {
      "startDate": "2025-04-26T16:06:00.114Z",
      "endDate": "2027-04-12T15:42:27.614Z",
      "status": "active",
      "tier": "basic",
      "features": {
        "autoRemediation": false,
        "realTimeMonitoring": true,
        "customPolicies": false,
        "deviceDiscovery": true,
        "apiAccess": false,
        "towerEnforcement": false,
        "appMonitoring": true
      }
    }
  },
  {
    "id": "ent_00000009",
    "name": "Keeling - D'Amore Ltd",
    "tier": "premium",
    "subscription": {
      "startDate": "2025-01-06T09:38:38.118Z",
      "endDate": "2026-12-04T13:11:48.173Z",
      "status": "active",
      "tier": "enterprise",
      "features": {
        "autoRemediation": true,
        "realTimeMonitoring": true,
        "customPolicies": true,
        "deviceDiscovery": true,
        "apiAccess": true,
        "towerEnforcement": true,
        "appMonitoring": true
      }
    }
  },
  {
    "id": "ent_00000010",
    "name": "Heathcote LLC Ltd",
    "tier": "premium",
    "subscription": {
      "startDate": "2024-10-27T03:25:07.515Z",
      "endDate": "2026-08-14T08:07:33.563Z",
      "status": "active",
      "tier": "enterprise",
      "features": {
        "autoRemediation": true,
        "realTimeMonitoring": true,
        "customPolicies": true,
        "deviceDiscovery": true,
        "apiAccess": true,
        "towerEnforcement": true,
        "appMonitoring": true
      }
    }
  }
]